LICENSE
MANIFEST.in
README.md
requirements.txt
setup.cfg
setup.py
py3wirecard/__init__.py
py3wirecard.egg-info/PKG-INFO
py3wirecard.egg-info/SOURCES.txt
py3wirecard.egg-info/dependency_links.txt
py3wirecard.egg-info/requires.txt
py3wirecard.egg-info/top_level.txt
py3wirecard/entities/__init__.py
py3wirecard/entities/acquirerdetails.py
py3wirecard/entities/address.py
py3wirecard/entities/amount.py
py3wirecard/entities/bankdebit.py
py3wirecard/entities/boleto.py
py3wirecard/entities/boletoinstructionlines.py
py3wirecard/entities/cancellationdetail.py
py3wirecard/entities/checkoutpreferences.py
py3wirecard/entities/creditcard.py
py3wirecard/entities/customer.py
py3wirecard/entities/device.py
py3wirecard/entities/entrie.py
py3wirecard/entities/escrow.py
py3wirecard/entities/event.py
py3wirecard/entities/fee.py
py3wirecard/entities/fundinginstrument.py
py3wirecard/entities/geolocation.py
py3wirecard/entities/holder.py
py3wirecard/entities/installments.py
py3wirecard/entities/moipaccount.py
py3wirecard/entities/notification.py
py3wirecard/entities/order.py
py3wirecard/entities/payment.py
py3wirecard/entities/phone.py
py3wirecard/entities/product.py
py3wirecard/entities/receiver.py
py3wirecard/entities/receiverdebited.py
py3wirecard/entities/redirecthref.py
py3wirecard/entities/redirecturls.py
py3wirecard/entities/refund.py
py3wirecard/entities/subtotals.py
py3wirecard/entities/taxdocument.py
py3wirecard/entities/webhook.py
py3wirecard/entities/webhooks.py
py3wirecard/entities/lib/__init__.py
py3wirecard/entities/lib/datatype.py
py3wirecard/entities/lib/wireentity.py
py3wirecard/models/__init__.py
py3wirecard/models/customer.py
py3wirecard/models/notification.py
py3wirecard/models/order.py
py3wirecard/models/payment.py
py3wirecard/models/refund.py
py3wirecard/models/webhooks.py
py3wirecard/utils/__init__.py
py3wirecard/utils/constants.py
py3wirecard/utils/util.py
test/test.py