Metadata-Version: 2.1
Name: py3wirecard
Version: 0.0.3
Summary: Wirecard API v2 Wrapper
Home-page: https://github.com/robertons/py3wirecard
Author: Roberto Neves
Author-email: robertonsilva@gmail.com
License: MIT
Keywords: wirecard,payment,payments,credit-card,boleto,moip
Platform: UNKNOWN
Classifier: Development Status :: 3 - Alpha
Classifier: Environment :: Web Environment
Classifier: Intended Audience :: Developers
Classifier: Natural Language :: English
Classifier: Natural Language :: Portuguese (Brazilian)
Classifier: License :: OSI Approved :: MIT License
Classifier: Programming Language :: Python :: 3.6
